{"cameraMode":{"drawMode":0,"name":"Shaded","section":"Shading Mode"},"sceneLighting":true,"audioPlay":false,"sceneViewState":{"showFog":true,"showMaterialUpdate":false,"showSkybox":true,"showFlares":true,"showImageEffects":true,"showParticleSystems":true},"in2DMode":false,"pivot":{"x":0.32041946053504946,"y":3.8674869537353517,"z":-1.9225568771362305},"rotation":{"x":0.5071131587028503,"y":0.012927206233143807,"z":-0.00760726910084486,"w":0.861748993396759},"size":18.797298431396486,"orthographic":false}