{"cameraMode":{"drawMode":0,"name":"Shaded","section":"Shading Mode"},"sceneLighting":true,"audioPlay":false,"sceneViewState":{"showFog":true,"showMaterialUpdate":false,"showSkybox":true,"showFlares":true,"showImageEffects":true,"showParticleSystems":true},"in2DMode":false,"pivot":{"x":1.609999656677246,"y":4.628403663635254,"z":51.53500747680664},"rotation":{"x":0.4602418541908264,"y":-0.08895143866539002,"z":0.046410754323005679,"w":0.8821077346801758},"size":224.11767578125,"orthographic":false}